pytest_scenarios/__init__.py
pytest_scenarios/py.typed
pytest_scenarios/pytest_fixtures.py
pytest_scenarios/scenario.py
pytest_scenarios/template_loader.py
pytest_scenarios-0.2.1.dist-info/WHEEL
pytest_scenarios-0.2.1.dist-info/entry_points.txt
pytest_scenarios-0.2.1.dist-info/METADATA
pytest_scenarios-0.2.1.dist-info/RECORD
