Metadata-Version: 2.3
Name: pytest-scenarios
Version: 0.2.1
Summary: Add your description here
Author: Carlos Martin Sanchez
Author-email: Carlos Martin Sanchez <carlosvin@gmail.com>
Requires-Python: >=3.9
